auto_verify-1.0.0.dist-info/licenses/LICENSE
autoverify/__init__.py
autoverify/config.py
autoverify/types.py
autoverify/cli/__init__.py
autoverify/cli/__main__.py
autoverify/cli/main.py
autoverify/cli/install/__init__.py
autoverify/cli/install/install.py
autoverify/cli/install/installers/__init__.py
autoverify/cli/install/installers/abcrown/__init__.py
autoverify/cli/install/installers/abcrown/environment.yml
autoverify/cli/install/installers/abcrown/install.py
autoverify/cli/install/installers/mnbab/__init__.py
autoverify/cli/install/installers/mnbab/environment.yml
autoverify/cli/install/installers/mnbab/install.py
autoverify/cli/install/installers/nnenum/__init__.py
autoverify/cli/install/installers/nnenum/environment.yml
autoverify/cli/install/installers/nnenum/install.py
autoverify/cli/install/installers/ovalbab/__init__.py
autoverify/cli/install/installers/ovalbab/environment.yml
autoverify/cli/install/installers/ovalbab/install.py
autoverify/cli/install/installers/sdpcrown/__init__.py
autoverify/cli/install/installers/sdpcrown/environment.yml
autoverify/cli/install/installers/sdpcrown/install.py
autoverify/cli/install/installers/verinet/__init__.py
autoverify/cli/install/installers/verinet/environment.yml
autoverify/cli/install/installers/verinet/install.py
autoverify/cli/install/venv_installers/__init__.py
autoverify/cli/install/venv_installers/venv_install.py
autoverify/cli/install/venv_installers/abcrown/venv_install.py
autoverify/cli/install/venv_installers/mnbab/venv_install.py
autoverify/cli/install/venv_installers/nnenum/venv_install.py
autoverify/cli/install/venv_installers/ovalbab/__init__.py
autoverify/cli/install/venv_installers/ovalbab/venv_install.py
autoverify/cli/install/venv_installers/verinet/venv_install.py
autoverify/cli/util/__init__.py
autoverify/cli/util/git.py
autoverify/portfolio/__init__.py
autoverify/portfolio/portfolio.py
autoverify/portfolio/portfolio_runner.py
autoverify/portfolio/hydra/__init__.py
autoverify/portfolio/hydra/cost_matrix.py
auto_verify-1.0.0.dist-info/METADATA
auto_verify-1.0.0.dist-info/WHEEL
auto_verify-1.0.0.dist-info/entry_points.txt
auto_verify-1.0.0.dist-info/top_level.txt
auto_verify-1.0.0.dist-info/RECORD
