Metadata-Version: 2.4
Name: auto-verify
Version: 1.0.0
Summary: Efficient portfolio-based verification of neural network properties
Author: Corné Spek, Hendrik Baacke, Jan van Rijn
License-Expression: BSD-3-Clause
Keywords: auto-verify,Neural networks,Robustness
Classifier: Operating System :: Unix
Classifier: Programming Language :: Python :: 3.10
Requires-Python: >=3.10
License-File: LICENSE
Requires-Dist: ConfigSpace==0.7.1
Requires-Dist: SMAC==2.0.2
Requires-Dist: result==0.9.0
Requires-Dist: xdg-base-dirs==6.0.1
Requires-Dist: onnxruntime==1.18.0
Requires-Dist: pandas==2.2.0
Requires-Dist: numpy<2,>=1.26.0
Requires-Dist: onnx==1.17.0
Requires-Dist: protobuf>=4.25.8
Requires-Dist: swig==4.1.1.post1
Requires-Dist: tomli>=2.0.0; python_version < "3.11"
Requires-Dist: tomli-w>=1.0.0
Provides-Extra: dev
Requires-Dist: ruff; extra == "dev"
Requires-Dist: tox; extra == "dev"
Requires-Dist: pytest==7.3.2; extra == "dev"
Requires-Dist: pre-commit; extra == "dev"
Requires-Dist: mypy; extra == "dev"
Requires-Dist: bumpver; extra == "dev"
Requires-Dist: coverage; extra == "dev"
Requires-Dist: mkdocs; extra == "dev"
Requires-Dist: pydocstyle; extra == "dev"
Requires-Dist: types-PyYAML; extra == "dev"
Requires-Dist: pytest-lazy-fixture==0.6.3; extra == "dev"
Dynamic: license-file
